example/__init__.py
example/run_app.py
udl_cil/__init__.py
udl_cil/optuna_pruner.py
udl_cil/utils_log.py
udl_cil/example/__init__.py
udl_cil/example/run_app.py
udl_cil/v2/__init__.py
udl_cil/v2/udl_cil.py
v2/__init__.py
v2/udl_cil.py
udl_cil-0.2.dist-info/METADATA
udl_cil-0.2.dist-info/WHEEL
udl_cil-0.2.dist-info/entry_points.txt
udl_cil-0.2.dist-info/top_level.txt
udl_cil-0.2.dist-info/RECORD
